conics/__about__.py
conics/__init__.py
conics/_conic.py
conics/_ellipse.py
conics/_harker.py
conics/_nievergelt.py
conics/_parabola.py
conics/fitting.py
conics/geometry.py
conics-0.1.0a2.dist-info/METADATA
conics-0.1.0a2.dist-info/WHEEL
conics-0.1.0a2.dist-info/licenses/LICENSE
conics-0.1.0a2.dist-info/RECORD
